tibacktester/__init__.py
tibacktester/cache.py
tibacktester/common.py
tibacktester/config.py
tibacktester/context.py
tibacktester/data.py
tibacktester/eval.py
tibacktester/indicator.py
tibacktester/log.py
tibacktester/model.py
tibacktester/portfolio.py
tibacktester/py.typed
tibacktester/scope.py
tibacktester/slippage.py
tibacktester/strategy.py
tibacktester/vect.py
tibacktester/ext/__init__.py
tibacktester/ext/data.py
tibacktester-25.7.8.dist-info/licenses/LICENSE
tibacktester-25.7.8.dist-info/METADATA
tibacktester-25.7.8.dist-info/WHEEL
tibacktester-25.7.8.dist-info/top_level.txt
tibacktester-25.7.8.dist-info/RECORD
