Metadata-Version: 2.4
Name: tibacktester
Version: 25.7.8
Summary: TI-Backtester, yet another quantitative trading library.
Author: tim-hub
License: Apache
Project-URL: homepage, https://github.com/TradeInsight-Info/tibacktester
Keywords: Algorithm Trading,Backtesting
Classifier: Programming Language :: Python :: 3
Requires-Python: <=3.13,>=3.12
License-File: LICENSE
Requires-Dist: akshare>=1.10.1
Requires-Dist: alpaca-py>=0.7.2
Requires-Dist: diskcache>=5.4.0
Requires-Dist: dotenv>=0.9.9
Requires-Dist: flake8>=5.0.4
Requires-Dist: flake8-bugbear>=22.10.25
Requires-Dist: joblib>=1.2.0
Requires-Dist: jupyter>=1.0.0
Requires-Dist: matplotlib>=3.9.1
Requires-Dist: nbsphinx>=0.8.11
Requires-Dist: numba>=0.60.0
Requires-Dist: numpy>=2.0.2
Requires-Dist: pandas>=2.2.0
Requires-Dist: progressbar2>=4.1.1
Requires-Dist: pytz>=2025.2
Requires-Dist: schedule>=1.2.2
Requires-Dist: scikit-learn>=1.5.1
Requires-Dist: scikit-optimize>=0.10.2
Requires-Dist: seaborn>=0.13.2
Requires-Dist: sphinx<8,>=5.3.0
Requires-Dist: sphinx-intl>=2.1.0
Requires-Dist: sphinx-rtd-theme>=2.0.0
Requires-Dist: ta-lib==0.6.4
Requires-Dist: tensorflow>=2.19.0
Requires-Dist: tqdm>=4.67.1
Requires-Dist: yahooquery>=2.3.7
Requires-Dist: yfinance>=0.2.55
Dynamic: license-file
